README.md
setup.py
gh0st/__init__.py
gh0st/__main__.py
gh0st.egg-info/PKG-INFO
gh0st.egg-info/SOURCES.txt
gh0st.egg-info/dependency_links.txt
gh0st.egg-info/entry_points.txt
gh0st.egg-info/top_level.txt
gh0st/packages/__init__.py
gh0st/packages/aart/__init__.py
gh0st/packages/aart/aart.py
gh0st/packages/aart/aart.txt
gh0st/packages/aart/cursed.py
gh0st/packages/keymap/__init__.py
gh0st/packages/keymap/keymap.py
gh0st/packages/menu/__init__.py
gh0st/packages/menu/menu.py
gh0st/packages/menu/option.py