Metadata-Version: 2.1
Name: gh0st
Version: 0.0.1
Summary: Top down stealth & hacking game
Home-page: https://gitlab.com/pyrogue6/gh0st
Author: Sabrina Held
Author-email: pyrogue6@gmail.com
License: GPLV3
Download-URL: https://gitlab.com/pyrogue6/gh0st/-/archive/0.0.1/gh0st-0.0.1.tar.gz
Keywords: stealth hacking puzzle game
Platform: UNKNOWN
Classifier: Development Status :: 1 - Planning
Classifier: License :: OSI Approved :: GNU General Public License v3 or later (GPLv3+)
Classifier: Environment :: Console :: Curses
Classifier: Intended Audience :: End Users/Desktop
Classifier: Topic :: Games/Entertainment :: Turn Based Strategy
Classifier: Topic :: Games/Entertainment :: Puzzle Games
Classifier: Programming Language :: Python :: 3.7
Classifier: Programming Language :: Python :: 3.8
Requires-Python: >=3
